{
  "project_info": {
    "project_number": "412041149923",
    "project_id": "moovies-9d184",
    "storage_bucket": "moovies-9d184.appspot.com"
  },
  "client": [
    {
      "client_info": {
        "mobilesdk_app_id": "1:412041149923:android:d2eed4d584c15839a134d6",
        "android_client_info": {
          "package_name": "com.fakdl.moovies"
        }
      },
      "oauth_client": [
        {
          "client_id": "412041149923-l5ujhu58p325sfi7hi97tk3noac2kgi6.apps.googleusercontent.com",
          "client_type": 1,
          "android_info": {
            "package_name": "com.fakdl.moovies",
            "certificate_hash": "938922fc4404e25107658281c89645747f57c859"
          }
        },
        {
          "client_id": "412041149923-lth4ta7i4phjnr64shqvai42g6df5rri.apps.googleusercontent.com",
          "client_type": 3
        }
      ],
      "api_key": [
        {
          "current_key": "AIzaSyAawam3Myh2BJUUgld0XVnCiWCUHmyD9uo"
        }
      ],
      "services": {
        "appinvite_service": {
          "other_platform_oauth_client": [
            {
              "client_id": "412041149923-lth4ta7i4phjnr64shqvai42g6df5rri.apps.googleusercontent.com",
              "client_type": 3
            }
          ]
        }
      }
    }
  ],
  "configuration_version": "1"
}